pcs/__init__.py
pcs/argument_parser.py
pcs/component.py
pcs/init.py
pcs/pipeline.py
pipeline_component_system-0.4.1.dist-info/licenses/LICENSE
pipeline_component_system-0.4.1.dist-info/METADATA
pipeline_component_system-0.4.1.dist-info/WHEEL
pipeline_component_system-0.4.1.dist-info/top_level.txt
pipeline_component_system-0.4.1.dist-info/RECORD
