Metadata-Version: 2.4
Name: pipeline-component-system
Version: 0.4.1
Summary: A strange programming framework
Author: Daniel Cauchi
Project-URL: Homepage, https://github.com/CowKeyMan/PCS
Project-URL: Issues, https://github.com/CowKeyMan/PCS/issues
Classifier: Development Status :: 4 - Beta
Classifier: License :: OSI Approved :: MIT No Attribution License (MIT-0)
Classifier: Operating System :: POSIX :: Linux
Classifier: Programming Language :: Python :: 3 :: Only
Classifier: Natural Language :: English
Classifier: Intended Audience :: Developers
Requires-Python: >=3.11
License-File: LICENSE
Requires-Dist: oyaml==1.0
Requires-Dist: omegaconf==2.3.0
Dynamic: license-file
